DreamMultiDevices/Performance.py
DreamMultiDevices/__init__.py
DreamMultiDevices/config.ini
DreamMultiDevices/start.py
DreamMultiDevices/TestCase/TC_101.py
DreamMultiDevices/TestCase/TC_102.py
DreamMultiDevices/TestCase/TC_103.py
DreamMultiDevices/TestCase/TC_104.py
DreamMultiDevices/TestCase/__init__.py
DreamMultiDevices/core/MultiAdb.py
DreamMultiDevices/core/RunTestCase.py
DreamMultiDevices/core/__init__.py
DreamMultiDevices/core/index.py
DreamMultiDevices/core/tmp.txt
DreamMultiDevices/template/__init__.py
DreamMultiDevices/tools/Config.py
DreamMultiDevices/tools/Email.py
DreamMultiDevices/tools/Excel.py
DreamMultiDevices/tools/File.py
DreamMultiDevices/tools/Init_MiniCap.py
DreamMultiDevices/tools/Json.py
DreamMultiDevices/tools/ScreenOFF.py
DreamMultiDevices/tools/Screencap.py
DreamMultiDevices/tools/TimeOut.py
DreamMultiDevices/tools/__init__.py
DreamMultiDevices-1.25.dist-info/LICENSE.txt
DreamMultiDevices-1.25.dist-info/METADATA
DreamMultiDevices-1.25.dist-info/WHEEL
DreamMultiDevices-1.25.dist-info/top_level.txt
DreamMultiDevices-1.25.dist-info/RECORD
