Metadata-Version: 2.1
Name: DreamMultiDevices
Version: 1.25
Summary: 给adb加了过滤关键字的功能
Home-page: https://github.com/saint228/DreamMultiDevices
Author: 无声andTreize
Author-email: saint_228@126.com
License: UNKNOWN
Platform: UNKNOWN
Classifier: License :: OSI Approved :: MIT License
Classifier: Intended Audience :: Developers
Classifier: Operating System :: OS Independent
Classifier: Programming Language :: Python
Classifier: Programming Language :: Python :: 3
Classifier: Programming Language :: Python :: 3.3
Classifier: Programming Language :: Python :: 3.4
Classifier: Programming Language :: Python :: 3.5
Classifier: Programming Language :: Python :: 3.6
Classifier: Programming Language :: Python :: 3.7
Requires-Dist: airtest (>=1.0.26)
Requires-Dist: BeautifulReport (>=0.0.9)
Requires-Dist: pocoui (>=1.0.76)
Requires-Dist: xlwings (>=0.15.8)
